featuretools4s
