Metadata-Version: 1.2
Name: featuretools4s
Version: 0.1.5
Summary: Run FeatureTools to automate Feature Engineering distributionally on Spark. 
Home-page: https://github.com/pan5431333/featuretools4s
Author: Meng Pan
Author-email: meng.pan95@gmail.com
Maintainer: Meng Pan
Maintainer-email: meng.pan95@gmail.com
License: BSD License
Platform: all
Classifier: Development Status :: 4 - Beta
Classifier: Operating System :: OS Independent
Classifier: Intended Audience :: Developers
Classifier: License :: OSI Approved :: BSD License
Classifier: Programming Language :: Python :: 3
Classifier: Programming Language :: Python :: 3.4
Classifier: Programming Language :: Python :: 3.5
Classifier: Programming Language :: Python :: 3.6
Classifier: Topic :: Software Development :: Libraries
